gaussprot/__init__.py
gaussprot/main.py
gaussprot-0.0.2.dist-info/METADATA
gaussprot-0.0.2.dist-info/WHEEL
gaussprot-0.0.2.dist-info/licenses/LICENSE
gaussprot-0.0.2.dist-info/RECORD
