Metadata-Version: 2.3
Name: gaussprot
Version: 0.0.2
Summary: Utility for generating Gaussian kernel models of proteins
Project-URL: Homepage, https://github.com/stefs304/gaussprot
Project-URL: Issues, https://github.com/stefs304/gaussprot/issues
Author-email: Stefan Stojanovic <stefs304@gmail.com>
License:                     GNU GENERAL PUBLIC LICENSE
License-File: LICENSE
Classifier: Intended Audience :: Science/Research
Classifier: License :: OSI Approved :: GNU General Public License v3 (GPLv3)
Classifier: Operating System :: OS Independent
Classifier: Programming Language :: Python :: 3
Classifier: Topic :: Scientific/Engineering :: Bio-Informatics
Requires-Python: >=3.9
Requires-Dist: numpy
